MANIFEST.in
README.rst
requirements.txt
setup.py
version.txt
bin/psychic_disco
psychic_disco/__init__.py
psychic_disco/api_gateway_config.py
psychic_disco/cli.py
psychic_disco/config.py
psychic_disco/deployment_package.py
psychic_disco/lambda_function.py
psychic_disco/rest_api.py
psychic_disco/rest_method.py
psychic_disco/rest_resource.py
psychic_disco.egg-info/PKG-INFO
psychic_disco.egg-info/SOURCES.txt
psychic_disco.egg-info/dependency_links.txt
psychic_disco.egg-info/not-zip-safe
psychic_disco.egg-info/requires.txt
psychic_disco.egg-info/top_level.txt
psychic_disco/tests/__init__.py
psychic_disco/tests/example_package.py
psychic_disco/tests/example_package_two.py
psychic_disco/tests/test_api.py
psychic_disco/tests/test_deployment_package.py
psychic_disco/tests/test_lambda_function.py
psychic_disco/tests/test_rest_api.py
psychic_disco/tests/test_rest_method.py
psychic_disco/tests/test_rest_resource.py
psychic_disco/tests/test_api_gateway_config/__init__.py
psychic_disco/tests/test_api_gateway_config/fake_gateway.py
psychic_disco/tests/util/__init__.py
psychic_disco/tests/util/test_util.py
psychic_disco/util/__init__.py