Metadata-Version: 1.0
Name: psychic-disco
Version: 0.10.2
Summary: Pythonic Microservices on AWS Lambda
Home-page: http://github.com/robertdfrench/psychic-disco
Author: Robert D. French
Author-email: robert@robertdfrench.me
License: MIT
Platform: UNKNOWN
